{
  "id": "school-of-eternity-trials-patience-hamza-yusuf",
  "title": "School of Eternity — tribulation, patience, and the believer",
  "scholar": "Shaykh Hamza Yusuf",
  "videoId": "H__bq1bD4Kg",
  "videoUrl": "https://www.youtube.com/watch?v=H__bq1bD4Kg",
  "datePublished": "2021-07-11",
  "tags": [
    "trials",
    "sabr",
    "patience",
    "gratitude",
    "Qur'an",
    "Surah Baqarah",
    "hadith believer",
    "Kierkegaard",
    "tribulation islam",
    "why does Allah test us",
    "dunya",
    "imperfection",
    "Hamza Yusuf",
    "Sandala"
  ],
  "category": "Trials & the Soul",
  "stanceSummary": "Trials are woven into life; the Qur’an and hadith frame patience in obedience and gratitude in ease as the believer’s response. Reflections link classical themes—Zarruq, Imam al-Junayd, and the hadith that the believer’s whole affair is good—to accepting the world’s imperfection without despair. Auto-captions below are cleaned for reading; confirm wording against the audio.",
  "transcriptFile": "H__bq1bD4Kg.md",
  "alternateQuestions": [
    "Why does Islam say trials are good for the believer?",
    "What does patience mean in Islam—not just waiting?",
    "How should Muslims respond to loss and fear?",
    "What is the hadith about the affair of the believer?"
  ]
}
